setup.cfg
setup.py
drf_related_views.egg-info/PKG-INFO
drf_related_views.egg-info/SOURCES.txt
drf_related_views.egg-info/dependency_links.txt
drf_related_views.egg-info/pbr.json
drf_related_views.egg-info/requires.txt
drf_related_views.egg-info/top_level.txt
rest_framework_related/__init__.py
rest_framework_related/filters.py
rest_framework_related/mixins.py
rest_framework_related/py2_3.py
rest_framework_related/utility.py
rest_framework_related/views.py